[
  {
    "id": "1559966781",
    "name_ru": "Наклейки для сосков Hearts с пайетками и кисточками - Сиреневый",
    "name_uk": "Наклейки для сосків Hearts з паєтками та пензликами - Бузковий",
    "description_ru": "Наклейки для сосков Hearts с пайетками и кисточками. Материал клеющей основы: Силикон. Отделка: Пайетки. Размеры сердечка: 4,5 см х 5 см. Длина с кисточками: 13 см. Цвет: сиреневый",
    "description_uk": "Наклейки для сосков Hearts с пайетками и кисточками. Материал клеющей основы: Силикон. Отделка: Пайетки. Размеры сердечка: 4,5 см х 5 см. Длина с кисточками: 13 см. Цвет: сиреневый",
    "price": 76,
    "oldprice": 84,
    "images": [
      "https://images.prom.ua/3824452429_naklejki-dlya-soskov.jpg",
      "https://images.prom.ua/6460043152_naklejki-dlya-soskov.jpg"
    ],
    "categoryId": "105010125",
    "available": true,
    "category": "lingerie",
    "params": [
      {
        "name": "Цвет",
        "value": "Фиолетовый"
      },
      {
        "name": "Международный размер",
        "value": "One size"
      }
    ]
  },
  {
    "id": "1559966783",
    "name_ru": "Прозрачный эротический игровой костюм \"Горничная\" - S/M",
    "name_uk": "Еротичний ігровий костюм \"Покоївка\" - S/M",
    "description_ru": "Костюм горничной. Размер S-M. Материал: 80% полиамид, 20% эластан.",
    "description_uk": "Костюм горничной. Размер S-M. Материал: 80% полиамид, 20% эластан.",
    "price": 148,
    "oldprice": 165,
    "images": [
      "https://images.prom.ua/7028661861_prozrachnyj-eroticheskij-igrovoj.jpg",
      "https://images.prom.ua/7028661863_prozrachnyj-eroticheskij-igrovoj.jpg",
      "https://images.prom.ua/7028661865_prozrachnyj-eroticheskij-igrovoj.jpg"
    ],
    "categoryId": "105010124",
    "available": true,
    "category": "lingerie",
    "params": [
      {
        "name": "Цвет",
        "value": "Черный"
      },
      {
        "name": "Международный размер",
        "value": "S/M"
      },
      {
        "name": "Тип ткани",
        "value": "Полиамид"
      }
    ]
  },
  {
    "id": "1559966784",
    "name_ru": "Прозрачный игровой костюм \"Медсестра\" - М/L - Белый",
    "name_uk": "Прозорий ігровий костюм \"Медсестра\" - М/L - Білий",
    "description_ru": "Короткий пеньюар на тонких бретельках. Материал: 80% полиамид, 20% эластан. Размер M/L.",
    "description_uk": "Короткий пеньюар на тонких бретельках. Материал: 80% полиамид, 20% эластан. Размер M/L.",
    "price": 270,
    "oldprice": null,
    "images": [
      "https://images.prom.ua/7008800457_prozrachnyj-igrovoj-kostyum.jpg",
      "https://images.prom.ua/7008800458_prozrachnyj-igrovoj-kostyum.jpg"
    ],
    "categoryId": "105010124",
    "available": false,
    "category": "lingerie",
    "params": [
      {
        "name": "Цвет",
        "value": "Белый"
      },
      {
        "name": "Международный размер",
        "value": "M/L"
      }
    ]
  },
  {
    "id": "1559966786",
    "name_ru": "Эротический костюм школьницы для ролевых игр - XS/S",
    "name_uk": "Еротичний костюм школярки для рольових ігор - XS/S",
    "description_ru": "Сексуальный топ и коротенькая юбка. Подходит на размер XS/S.",
    "description_uk": "Сексуальный топ и коротенькая юбка. Подходит на размер XS/S.",
    "price": 345,
    "oldprice": null,
    "images": [
      "https://images.prom.ua/7006072118_eroticheskij-kostyum-shkolnitsy.jpg",
      "https://images.prom.ua/7006072120_eroticheskij-kostyum-shkolnitsy.jpg"
    ],
    "categoryId": "105010124",
    "available": false,
    "category": "lingerie",
    "params": [
      {
        "name": "Цвет",
        "value": "Белый"
      },
      {
        "name": "Международный размер",
        "value": "XS-S"
      }
    ]
  },
  {
    "id": "1559966789",
    "name_ru": "Эротический игровой костюм \"Подарок\" - S/M/L - Красный",
    "name_uk": "Еротичний ігровий костюм \"Подарунок\" - S/M/L - Червоний",
    "description_ru": "Монокини и лента из атласного материала. Материал: 100% полиамид. Размер S/M/L.",
    "description_uk": "Монокини и лента из атласного материала. Материал: 100% полиамид. Размер S/M/L.",
    "price": 154,
    "oldprice": 172,
    "images": [
      "https://images.prom.ua/7008800895_eroticheskij-igrovoj-kostyum.jpg",
      "https://images.prom.ua/6460020603_eroticheskij-igrovoj-kostyum.jpg"
    ],
    "categoryId": "105010124",
    "available": true,
    "category": "lingerie",
    "params": [
      {
        "name": "Цвет",
        "value": "Красный"
      },
      {
        "name": "Международный размер",
        "value": "S/M/L"
      }
    ]
  },
  {
    "id": "1559966791",
    "name_ru": "Игровой костюм \"Пленница\" - XS/S/M - Красный",
    "name_uk": "Ігровий костюм \"Полонянка\" - XS/S/M - Червоний",
    "description_ru": "Бюстгальтер с открытыми чашечками, тканевые наручники. Материал: 80% полиамид, 20% эластан. Размер XS/S/M.",
    "description_uk": "Бюстгальтер с открытыми чашечками, тканевые наручники. Материал: 80% полиамид, 20% эластан. Размер XS/S/M.",
    "price": 105,
    "oldprice": 118,
    "images": [
      "https://images.prom.ua/7034040110_igrovoj-kostyum-plennitsa.jpg",
      "https://images.prom.ua/7034040111_igrovoj-kostyum-plennitsa.jpg"
    ],
    "categoryId": "105010124",
    "available": true,
    "category": "lingerie",
    "params": [
      {
        "name": "Цвет",
        "value": "Красный"
      },
      {
        "name": "Международный размер",
        "value": "S/M"
      }
    ]
  },
  {
    "id": "1559966792",
    "name_ru": "Игровой костюм медсестры - XS/S - Белый",
    "name_uk": "Ігровий костюм медсестри - XS/S - Білий",
    "description_ru": "Прозрачный короткий пеньюар. Две подвязки с бантиками. Материал: 100% полиамид. Размер XS/S.",
    "description_uk": "Прозрачный короткий пеньюар. Две подвязки с бантиками. Материал: 100% полиамид. Размер XS/S.",
    "price": 177,
    "oldprice": null,
    "images": [
      "https://images.prom.ua/7034824946_igrovoj-kostyum-medsestry.jpg",
      "https://images.prom.ua/7034824947_igrovoj-kostyum-medsestry.jpg"
    ],
    "categoryId": "105010124",
    "available": false,
    "category": "lingerie",
    "params": [
      {
        "name": "Цвет",
        "value": "Белый"
      },
      {
        "name": "Международный размер",
        "value": "XS-S"
      }
    ]
  },
  {
    "id": "1559966793",
    "name_ru": "Ролевой костюм \"Зайка\" - XS",
    "name_uk": "Рольовий костюм \"Зайчик\" - XS",
    "description_ru": "Шортики с подтяжками, обруч с ушками, блузка. Материал: лайкра, спандекс. Размер XS.",
    "description_uk": "Шортики с подтяжками, обруч с ушками, блузка. Материал: лайкра, спандекс. Размер XS.",
    "price": 447,
    "oldprice": null,
    "images": [
      "https://images.prom.ua/7034824942_rolevoj-kostyum-zajka.jpg",
      "https://images.prom.ua/7034824943_rolevoj-kostyum-zajka.jpg"
    ],
    "categoryId": "105010124",
    "available": false,
    "category": "lingerie",
    "params": [
      {
        "name": "Цвет",
        "value": "Черный"
      },
      {
        "name": "Международный размер",
        "value": "XS"
      }
    ]
  },
  {
    "id": "1559966794",
    "name_ru": "Мужские трусы \"Бабочка\" - Красный - М-XL",
    "name_uk": "Чоловічі труси \"Метелик\" - Червоний - М-XL",
    "description_ru": "Эластичные резинки делают трусы универсальными. Состав: хлопок, спандекс. Размер от M до XL.",
    "description_uk": "Эластичные резинки делают трусы универсальными. Состав: хлопок, спандекс. Размер от M до XL.",
    "price": 166,
    "oldprice": 186,
    "images": [
      "https://images.prom.ua/7006065864_muzhskie-trusy-babochka.jpg",
      "https://images.prom.ua/7006065865_muzhskie-trusy-babochka.jpg"
    ],
    "categoryId": "105010129",
    "available": true,
    "category": "for-him",
    "params": [
      {
        "name": "Цвет",
        "value": "Красный"
      },
      {
        "name": "Тип ткани",
        "value": "Хлопок"
      }
    ]
  },
  {
    "id": "1559966795",
    "name_ru": "Стринги мужские \"Олень\" - L-XXXL",
    "name_uk": "Стрінги чоловічі \"Олень\" - L-XXXL",
    "description_ru": "Оригинальный дизайн. Материал: велюр. Размер L-XXXL.",
    "description_uk": "Оригинальный дизайн. Материал: велюр. Размер L-XXXL.",
    "price": 244,
    "oldprice": 275,
    "images": [
      "https://images.prom.ua/6460039306_stringi-muzhskie-olen.jpg",
      "https://images.prom.ua/6460039304_stringi-muzhskie-olen.jpg"
    ],
    "categoryId": "105010129",
    "available": true,
    "category": "for-him",
    "params": [
      {
        "name": "Цвет",
        "value": "Коричневый"
      },
      {
        "name": "Тип трусов",
        "value": "Стринги"
      }
    ]
  },
  {
    "id": "1559966796",
    "name_ru": "Игровой костюм \"Сексуальная невеста\" - XS/S/M - Белый",
    "name_uk": "Ігровий костюм \"Сексуальна наречена\" - XS/S/M - Білий",
    "description_ru": "Фата, платье, перчатки, подвязки, трусики. Размер XS/S/M.",
    "description_uk": "Фата, платье, перчатки, подвязки, трусики. Размер XS/S/M.",
    "price": 363,
    "oldprice": 406,
    "images": [
      "https://images.prom.ua/7032451432_igrovoj-kostyum-seksualnaya.jpg",
      "https://images.prom.ua/7032451433_igrovoj-kostyum-seksualnaya.jpg"
    ],
    "categoryId": "105010124",
    "available": true,
    "category": "lingerie",
    "params": [
      {
        "name": "Цвет",
        "value": "Белый"
      },
      {
        "name": "Тип ткани",
        "value": "Атлас"
      }
    ]
  },
  {
    "id": "1559966797",
    "name_ru": "Костюм \"Соблазнительной студентки\" - XS/S",
    "name_uk": "Костюм \"Спокусливої студентки\" - XS/S",
    "description_ru": "Топ, юбка, трусики, воротник, галстук. Размер XS/S.",
    "description_uk": "Топ, юбка, трусики, воротник, галстук. Размер XS/S.",
    "price": 525,
    "oldprice": null,
    "images": [
      "https://images.prom.ua/6460022477_kostyum-soblaznitelnoj-studentki.jpg",
      "https://images.prom.ua/6460022479_kostyum-soblaznitelnoj-studentki.jpg"
    ],
    "categoryId": "105010124",
    "available": false,
    "category": "lingerie",
    "params": [
      {
        "name": "Цвет",
        "value": "Красный"
      },
      {
        "name": "Международный размер",
        "value": "XS-S"
      }
    ]
  },
  {
    "id": "1559966798",
    "name_ru": "Эротический латексный костюм \"Пленница\" - S/M - Черный",
    "name_uk": "Еротичний латексний костюм \"Бранниця\" - S/M - Чорний",
    "description_ru": "Сексуальный латексный костюм с подвязками для чулок. Размер S/M.",
    "description_uk": "Сексуальный латексный костюм с подвязками для чулок. Размер S/M.",
    "price": 586,
    "oldprice": null,
    "images": [
      "https://images.prom.ua/6460020609_eroticheskij-lateksnyj-kostyum.jpg",
      "https://images.prom.ua/6460020610_eroticheskij-lateksnyj-kostyum.jpg"
    ],
    "categoryId": "105010124",
    "available": false,
    "category": "lingerie",
    "params": [
      {
        "name": "Цвет",
        "value": "Черный"
      },
      {
        "name": "Тип ткани",
        "value": "Латекс"
      }
    ]
  },
  {
    "id": "1559966800",
    "name_ru": "Ролевой костюм медсестры - S/M - Белый",
    "name_uk": "Рольовий костюм медсестри - S/M - Білий",
    "description_ru": "Невероятно сексуальное боди с чепчиком. Размер S/M.",
    "description_uk": "Невероятно сексуальное боди с чепчиком. Размер S/M.",
    "price": 213,
    "oldprice": 239,
    "images": [
      "https://images.prom.ua/6460023475_rolevoj-kostyum-medsestry.jpg",
      "https://images.prom.ua/6460023477_rolevoj-kostyum-medsestry.jpg"
    ],
    "categoryId": "105010124",
    "available": true,
    "category": "lingerie",
    "params": [
      {
        "name": "Цвет",
        "value": "Белый"
      },
      {
        "name": "Тип ткани",
        "value": "Хлопок"
      }
    ]
  },
  {
    "id": "1559966801",
    "name_ru": "Эротическая ажурная маска на глаза - Чёрный",
    "name_uk": "Еротична ажурна маска на очі - Чорний",
    "description_ru": "Кружевная маска на глаза из ажурного полотна. Размер универсальный.",
    "description_uk": "Кружевная маска на глаза из ажурного полотна. Размер универсальный.",
    "price": 34,
    "oldprice": 37,
    "images": [
      "https://images.prom.ua/7008790763_eroticheskaya-azhurnaya-maska.jpg",
      "https://images.prom.ua/7008790764_eroticheskaya-azhurnaya-maska.jpg"
    ],
    "categoryId": "105010125",
    "available": true,
    "category": "lingerie",
    "params": [
      {
        "name": "Цвет",
        "value": "Черный"
      },
      {
        "name": "Тип ткани",
        "value": "Кружево"
      }
    ]
  },
  {
    "id": "1559966805",
    "name_ru": "Мужские стринги комбинезон - Чёрный - М/L",
    "name_uk": "Чоловічі стрінги комбінезон - Чорний - М/L",
    "description_ru": "Мужской комбинезон-стринги. Материал: нейлон. Размер M/L.",
    "description_uk": "Мужской комбинезон-стринги. Материал: нейлон. Размер M/L.",
    "price": 128,
    "oldprice": 143,
    "images": [
      "https://images.prom.ua/7008795843_muzhskie-stringi-kombinezon.jpg",
      "https://images.prom.ua/7008795842_muzhskie-stringi-kombinezon.jpg"
    ],
    "categoryId": "105010129",
    "available": true,
    "category": "for-him",
    "params": [
      {
        "name": "Цвет",
        "value": "Черный"
      },
      {
        "name": "Тип трусов",
        "value": "Стринги"
      }
    ]
  },
  {
    "id": "1559966808",
    "name_ru": "Игровой костюм соблазнительной пленницы - S/M - Черный",
    "name_uk": "Ігровий костюм спокусливої полонянки - S/M - Чорний",
    "description_ru": "Бюстгальтер, трусики, кружевные наручники, повязка на глаза. Материал: 80% полиамид, 20% эластан. Размер S/M.",
    "description_uk": "Бюстгальтер, трусики, кружевные наручники, повязка на глаза. Материал: 80% полиамид, 20% эластан. Размер S/M.",
    "price": 160,
    "oldprice": 179,
    "images": [
      "https://images.prom.ua/6460020607_igrovoj-kostyum-soblaznitelnoj.jpg",
      "https://images.prom.ua/6460020606_igrovoj-kostyum-soblaznitelnoj.jpg"
    ],
    "categoryId": "105010124",
    "available": true,
    "category": "lingerie",
    "params": [
      {
        "name": "Цвет",
        "value": "Черный"
      },
      {
        "name": "Международный размер",
        "value": "S/M"
      }
    ]
  },
  {
    "id": "1559966809",
    "name_ru": "Мужские стринги \"Слоник\" - Красные - M/L/XL",
    "name_uk": "Чоловічі стрінги \"Слоник\" - Червоні - M/L/XL",
    "description_ru": "Мягкий материал, очень комфортные. Размер M, L, XL. Цвет: красный.",
    "description_uk": "Мягкий материал, очень комфортные. Размер M, L, XL. Цвет: красный.",
    "price": 76,
    "oldprice": 85,
    "images": [
      "https://images.prom.ua/7034823562_muzhskie-stringi-slonik.jpg",
      "https://images.prom.ua/7034038577_muzhskie-stringi-slonik.jpg"
    ],
    "categoryId": "105010129",
    "available": true,
    "category": "for-him",
    "params": [
      {
        "name": "Цвет",
        "value": "Красный"
      }
    ]
  },
  {
    "id": "1559966810",
    "name_ru": "Мужские стринги \"Слоник\" - Черный - М/L/XL",
    "name_uk": "Чоловічі стрінги \"Слоник\" - Чорний - М/L/XL",
    "description_ru": "Мягкий материал, очень комфортные. Размер M, L, XL. Цвет: черный.",
    "description_uk": "Мягкий материал, очень комфортные. Размер M, L, XL. Цвет: черный.",
    "price": 76,
    "oldprice": 85,
    "images": [
      "https://images.prom.ua/7034038577_muzhskie-stringi-slonik.jpg",
      "https://images.prom.ua/7034038578_muzhskie-stringi-slonik.jpg"
    ],
    "categoryId": "105010129",
    "available": true,
    "category": "for-him",
    "params": [
      {
        "name": "Цвет",
        "value": "Черный"
      }
    ]
  },
  {
    "id": "1559966818",
    "name_ru": "БодиСтокинг (Боди комбинезон Сетка) - Черный",
    "name_uk": "БодіСтокінг (Боді комбінезон Сітка) - Чорний",
    "description_ru": "Прозрачный бодистокинг в ромбовидную сетку. Материал: 93,4% полиамид, 6,6% эластан. Размер S/M/L.",
    "description_uk": "Прозрачный бодистокинг в ромбовидную сетку. Материал: 93,4% полиамид, 6,6% эластан. Размер S/M/L.",
    "price": 133,
    "oldprice": 147,
    "images": [
      "https://images.prom.ua/6460035919_bodistoking-bodi-kombinezon.jpg",
      "https://images.prom.ua/6460035921_bodistoking-bodi-kombinezon.jpg"
    ],
    "categoryId": "105010125",
    "available": true,
    "category": "lingerie",
    "params": [
      {
        "name": "Цвет",
        "value": "Черный"
      },
      {
        "name": "Тип ткани",
        "value": "Сетка"
      }
    ]
  },
  {
    "id": "1559966821",
    "name_ru": "Сексуальный боди комбинезон Сетка - S/M/L",
    "name_uk": "Сексуальний боді комбінезон Сітка - S/M/L",
    "description_ru": "Бодистокинг в круглую сетку с V-образным вырезом. Размер S/M/L.",
    "description_uk": "Бодистокинг в круглую сетку с V-образным вырезом. Размер S/M/L.",
    "price": 135,
    "oldprice": 148,
    "images": [
      "https://images.prom.ua/7034807436_seksualnyj-bodi-kombinezon.jpg",
      "https://images.prom.ua/7034807437_seksualnyj-bodi-kombinezon.jpg"
    ],
    "categoryId": "105010125",
    "available": true,
    "category": "lingerie",
    "params": [
      {
        "name": "Тип ткани",
        "value": "Сетка"
      }
    ]
  },
  {
    "id": "1559966825",
    "name_ru": "Эротический прозрачный БодиСтокинг - Чёрный - S/M/L",
    "name_uk": "Еротичний прозорий БодіСтокінг - Чорний - S/M/L",
    "description_ru": "Бодистокинг в сетку с геометрическим рисунком, длинный рукав. Размер S/M/L.",
    "description_uk": "Бодистокинг в сетку с геометрическим рисунком, длинный рукав. Размер S/M/L.",
    "price": 130,
    "oldprice": 144,
    "images": [
      "https://images.prom.ua/7034807440_eroticheskij-prozrachnyj-bodistoking.jpg",
      "https://images.prom.ua/7034807441_eroticheskij-prozrachnyj-bodistoking.jpg"
    ],
    "categoryId": "105010125",
    "available": true,
    "category": "lingerie",
    "params": [
      {
        "name": "Цвет",
        "value": "Черный"
      }
    ]
  },
  {
    "id": "1559966826",
    "name_ru": "Эротический прозрачный БодиСтокинг на бретельках - Чёрный",
    "name_uk": "Еротичний прозорий БодіСтокінг на бретельках - Чорний",
    "description_ru": "Бодистокинг на шести тонких бретельках. Материал: 93,4% полиамид, 6,6% эластан. Размер S/M/L.",
    "description_uk": "Бодистокинг на шести тонких бретельках. Материал: 93,4% полиамид, 6,6% эластан. Размер S/M/L.",
    "price": 117,
    "oldprice": 130,
    "images": [
      "https://images.prom.ua/7012386798_eroticheskij-prozrachnyj-bodistoking.jpg",
      "https://images.prom.ua/7012386799_eroticheskij-prozrachnyj-bodistoking.jpg"
    ],
    "categoryId": "105010125",
    "available": true,
    "category": "lingerie",
    "params": [
      {
        "name": "Цвет",
        "value": "Черный"
      }
    ]
  },
  {
    "id": "1559966827",
    "name_ru": "Эротический короткий Пеньюар \"Сетка\" - S/M/L",
    "name_uk": "Еротичний короткий Пеньюар \"Сітка\" - S/M/L",
    "description_ru": "Короткий пеньюар в ажурную ромбовидную сетку с длинным рукавом. Материал: 93,4% полиамид. Размер S/M/L.",
    "description_uk": "Короткий пеньюар в ажурную ромбовидную сетку с длинным рукавом. Материал: 93,4% полиамид. Размер S/M/L.",
    "price": 128,
    "oldprice": 141,
    "images": [
      "https://images.prom.ua/3591608684_eroticheskij-korotkij-penyuar.jpg",
      "https://images.prom.ua/7034807499_eroticheskij-korotkij-penyuar.jpg"
    ],
    "categoryId": "105010125",
    "available": true,
    "category": "lingerie",
    "params": []
  },
  {
    "id": "1559966828",
    "name_ru": "Эротический прозрачный \"Боди-Монокини\" - XS/S/M",
    "name_uk": "Еротичний прозорий \"Боді-Монокіні\" - XS/S/M",
    "description_ru": "Кокетливое сексуальное боди-монокини. Размер XS/S/M.",
    "description_uk": "Кокетливое сексуальное боди-монокини. Размер XS/S/M.",
    "price": 160,
    "oldprice": null,
    "images": [
      "https://images.prom.ua/7034807501_eroticheskij-prozrachnyj-bodi.jpg",
      "https://images.prom.ua/7034807502_eroticheskij-prozrachnyj-bodi.jpg"
    ],
    "categoryId": "105010125",
    "available": false,
    "category": "lingerie",
    "params": [
      {
        "name": "Цвет",
        "value": "Черный"
      }
    ]
  },
  {
    "id": "1559966839",
    "name_ru": "Секси комплект в сетку - Черный",
    "name_uk": "Сексі комплект у сітку - Чорний",
    "description_ru": "Откровенный комплект: топик, юбка, трусики из сетки. Размер S-M.",
    "description_uk": "Откровенный комплект: топик, юбка, трусики из сетки. Размер S-M.",
    "price": 201,
    "oldprice": 226,
    "images": [
      "https://images.prom.ua/7034807503_seksi-komplekt-v.jpg",
      "https://images.prom.ua/7034807504_seksi-komplekt-v.jpg"
    ],
    "categoryId": "105010125",
    "available": true,
    "category": "lingerie",
    "params": [
      {
        "name": "Цвет",
        "value": "Черный"
      },
      {
        "name": "Тип ткани",
        "value": "Сетка"
      }
    ]
  },
  {
    "id": "1559966849",
    "name_ru": "Беспроигрышный сексуальный комплект нижнего белья - Чёрный - XS/S/M",
    "name_uk": "Безпрограшний сексуальний комплект нижньої білизни - Чорний",
    "description_ru": "Материал: 80% полиамид, 20% эластан. Размер XS/S/M.",
    "description_uk": "Материал: 80% полиамид, 20% эластан. Размер XS/S/M.",
    "price": 62,
    "oldprice": 68,
    "images": [
      "https://images.prom.ua/7034807506_besproigryshnyj-seksualnyj-komplekt.jpg",
      "https://images.prom.ua/7034807507_besproigryshnyj-seksualnyj-komplekt.jpg"
    ],
    "categoryId": "105010125",
    "available": true,
    "category": "lingerie",
    "params": [
      {
        "name": "Цвет",
        "value": "Черный"
      }
    ]
  },
  {
    "id": "1559966850",
    "name_ru": "Эротический комплект со стразами - XS/S/М - Чёрный",
    "name_uk": "Еротичний комплект зі стразами - XS/S/М - Чорний",
    "description_ru": "Пеньюар-накидка, трусики-пояс для чулок, две подвязки. Материал: 85% полиамид, 15% эластан.",
    "description_uk": "Пеньюар-накидка, трусики-пояс для чулок, две подвязки. Материал: 85% полиамид, 15% эластан.",
    "price": 231,
    "oldprice": null,
    "images": [
      "https://images.prom.ua/7006059830_eroticheskij-komplekt-so.jpg",
      "https://images.prom.ua/6409451168_eroticheskij-komplekt-so.jpg"
    ],
    "categoryId": "105010125",
    "available": false,
    "category": "lingerie",
    "params": [
      {
        "name": "Цвет",
        "value": "Черный"
      }
    ]
  },
  {
    "id": "1559966852",
    "name_ru": "Чулки-сетка с кружевом - Чёрный - XS/S",
    "name_uk": "Панчохи-сітка з мереживом - Чорний - XS/S",
    "description_ru": "Сексуальные чулки-сетка с кружевом без силиконовой полоски. Размер XS/S.",
    "description_uk": "Сексуальные чулки-сетка с кружевом без силиконовой полоски. Размер XS/S.",
    "price": 48,
    "oldprice": 53,
    "images": [
      "https://images.prom.ua/7013701035_chulki-setka-s-kruzhevom.jpg",
      "https://images.prom.ua/7013701036_chulki-setka-s-kruzhevom.jpg"
    ],
    "categoryId": "105010125",
    "available": true,
    "category": "lingerie",
    "params": [
      {
        "name": "Цвет",
        "value": "Черный"
      }
    ]
  },
  {
    "id": "1559966853",
    "name_ru": "Чулки-сетка с кружевом - Красный - XS/S",
    "name_uk": "Панчохи-сітка з мереживом - Червоний - XS/S",
    "description_ru": "Сексуальные чулки-сетка с кружевом. Размер XS/S. Цвет: красный.",
    "description_uk": "Сексуальные чулки-сетка с кружевом. Размер XS/S. Цвет: красный.",
    "price": 48,
    "oldprice": 53,
    "images": [
      "https://images.prom.ua/7034807790_chulki-setka-s-kruzhevom.jpg"
    ],
    "categoryId": "105010125",
    "available": true,
    "category": "lingerie",
    "params": [
      {
        "name": "Цвет",
        "value": "Красный"
      }
    ]
  },
  {
    "id": "1559966875",
    "name_ru": "Стринги бабочка - Красный - XS/S/M",
    "name_uk": "Стрінги метелик - Червоний - XS/S/M",
    "description_ru": "Трусики акцентируют внимание на ягодицах. Размер XS/S/M.",
    "description_uk": "Трусики акцентируют внимание на ягодицах. Размер XS/S/M.",
    "price": 55,
    "oldprice": 61,
    "images": [
      "https://images.prom.ua/7013701040_stringi-babochka-.jpg",
      "https://images.prom.ua/7013701041_stringi-babochka-.jpg"
    ],
    "categoryId": "105010125",
    "available": true,
    "category": "lingerie",
    "params": [
      {
        "name": "Цвет",
        "value": "Красный"
      },
      {
        "name": "Тип трусов",
        "value": "T-стринги"
      }
    ]
  },
  {
    "id": "1559966876",
    "name_ru": "Стринги бабочка - Чёрный - XS/S/M",
    "name_uk": "Стрінги метелик - Чорний - XS/S/M",
    "description_ru": "Трусики акцентируют внимание на ягодицах. Размер XS/S/M.",
    "description_uk": "Трусики акцентируют внимание на ягодицах. Размер XS/S/M.",
    "price": 55,
    "oldprice": 61,
    "images": [
      "https://images.prom.ua/7013701189_stringi-babochka-.jpg",
      "https://images.prom.ua/7013701041_stringi-babochka-.jpg"
    ],
    "categoryId": "105010125",
    "available": true,
    "category": "lingerie",
    "params": [
      {
        "name": "Цвет",
        "value": "Черный"
      },
      {
        "name": "Тип трусов",
        "value": "T-стринги"
      }
    ]
  },
  {
    "id": "1559966880",
    "name_ru": "Плетка для ролевых игр \"Sexy\" - Розовый",
    "name_uk": "Батіг для рольових ігор \"Sexy\" - Рожевий",
    "description_ru": "Плетка в классическом стиле. Ручка 16 см, полоски 32 см. Материал: эко кожа.",
    "description_uk": "Плетка в классическом стиле. Ручка 16 см, полоски 32 см. Материал: эко кожа.",
    "price": 100,
    "oldprice": 111,
    "images": [
      "https://images.prom.ua/7034813963_pletka-dlya-rolevyh.jpg",
      "https://images.prom.ua/7006063109_pletka-dlya-rolevyh.jpg"
    ],
    "categoryId": "105010126",
    "available": true,
    "category": "bdsm",
    "params": [
      {
        "name": "Цвет",
        "value": "Розовый"
      },
      {
        "name": "Материал",
        "value": "Искусственная кожа"
      }
    ]
  },
  {
    "id": "1559966881",
    "name_ru": "Плетка для ролевых игр \"Sexy\" - Чёрный",
    "name_uk": "Батіг для рольових ігор \"Sexy\" - Чорний",
    "description_ru": "Плетка в классическом стиле. Ручка 16 см, полоски 32 см. Материал: эко кожа.",
    "description_uk": "Плетка в классическом стиле. Ручка 16 см, полоски 32 см. Материал: эко кожа.",
    "price": 100,
    "oldprice": 111,
    "images": [
      "https://images.prom.ua/7006063106_pletka-dlya-rolevyh.jpg",
      "https://images.prom.ua/7006063107_pletka-dlya-rolevyh.jpg"
    ],
    "categoryId": "105010126",
    "available": true,
    "category": "bdsm",
    "params": [
      {
        "name": "Цвет",
        "value": "Черный"
      },
      {
        "name": "Материал",
        "value": "Искусственная кожа"
      }
    ]
  },
  {
    "id": "1559966882",
    "name_ru": "Бондаж для рук и ног \"Scappa\" - Черный",
    "name_uk": "Бондаж для рук і ніг \"Scappa\" - Чорний",
    "description_ru": "Фиксатор из нейлона. Размер регулируется застежками-липучками.",
    "description_uk": "Фиксатор из нейлона. Размер регулируется застежками-липучками.",
    "price": 204,
    "oldprice": 224,
    "images": [
      "https://images.prom.ua/7034814012_bondazh-dlya-ruk.jpg",
      "https://images.prom.ua/7034814013_bondazh-dlya-ruk.jpg"
    ],
    "categoryId": "105010126",
    "available": true,
    "category": "bdsm",
    "params": [
      {
        "name": "Цвет",
        "value": "Черный"
      },
      {
        "name": "Материал",
        "value": "Металл"
      }
    ]
  },
  {
    "id": "1559966883",
    "name_ru": "Зажимы для сосков с колокольчиком - Черный",
    "name_uk": "Затискачі для сосків із дзвіночком - Чорний",
    "description_ru": "Зажимы для сосков с колокольчиком. Степень сжатия регулируется. Материал: металл, PU кожа.",
    "description_uk": "Зажимы для сосков с колокольчиком. Степень сжатия регулируется. Материал: металл, PU кожа.",
    "price": 58,
    "oldprice": 64,
    "images": [
      "https://images.prom.ua/7034814015_zazhimy-dlya-soskov.jpg",
      "https://images.prom.ua/7034814016_zazhimy-dlya-soskov.jpg"
    ],
    "categoryId": "105010126",
    "available": true,
    "category": "bdsm",
    "params": [
      {
        "name": "Цвет",
        "value": "Черный"
      },
      {
        "name": "Материал",
        "value": "Искусственная кожа"
      }
    ]
  },
  {
    "id": "1559966884",
    "name_ru": "Маска на глаза \"Pono\" - Чёрный",
    "name_uk": "Маска на очі \"Pono\" - Чорний",
    "description_ru": "Маска Pono для БДСМ игр или сна. Материал: полиэстер. Размер: 18,5 х 6 см.",
    "description_uk": "Маска Pono для БДСМ игр или сна. Материал: полиэстер. Размер: 18,5 х 6 см.",
    "price": 54,
    "oldprice": 59,
    "images": [
      "https://images.prom.ua/7010415387_maska-na-glaza.jpg",
      "https://images.prom.ua/7010415389_maska-na-glaza.jpg"
    ],
    "categoryId": "127921895",
    "available": true,
    "category": "lingerie",
    "params": [
      {
        "name": "Цвет",
        "value": "Черный"
      }
    ]
  },
  {
    "id": "1559966888",
    "name_ru": "Кляп \"Кость\" для BDSM - Красный",
    "name_uk": "Кляп \"Кістка\" для BDSM - Червоний",
    "description_ru": "БДСМ кляп в виде кости. Материал: силикон, эко кожа. Длина кляпа 12 см.",
    "description_uk": "БДСМ кляп в виде кости. Материал: силикон, эко кожа. Длина кляпа 12 см.",
    "price": 309,
    "oldprice": null,
    "images": [
      "https://images.prom.ua/7034814020_klyap-kost-v.jpg",
      "https://images.prom.ua/6409692998_klyap-kost-v.jpg"
    ],
    "categoryId": "105010126",
    "available": false,
    "category": "bdsm",
    "params": [
      {
        "name": "Цвет",
        "value": "Красный"
      },
      {
        "name": "Материал",
        "value": "Силикон"
      }
    ]
  },
  {
    "id": "1559966889",
    "name_ru": "Сексуальная маска кошки - Чёрный",
    "name_uk": "Сексуальна маска кішки - Чорний",
    "description_ru": "Кожаная маска кошки на регулирующейся резинке. Размер 20*15 см. Материал: эко-кожа, металл.",
    "description_uk": "Кожаная маска кошки на регулирующейся резинке. Размер 20*15 см. Материал: эко-кожа, металл.",
    "price": 157,
    "oldprice": 174,
    "images": [
      "https://images.prom.ua/7008792870_seksualnaya-maska-koshki.jpg",
      "https://images.prom.ua/7008792872_seksualnaya-maska-koshki.jpg"
    ],
    "categoryId": "127921895",
    "available": true,
    "category": "lingerie",
    "params": [
      {
        "name": "Цвет",
        "value": "Черный"
      },
      {
        "name": "Материал",
        "value": "Искусственная кожа"
      }
    ]
  },
  {
    "id": "1559966891",
    "name_ru": "Наручники \"Сладкие оковы\" - Чёрный",
    "name_uk": "Наручники \"Солодкі окови\" - Чорний",
    "description_ru": "Металлические наручники, покрытые мягким плюшем. Открываются ключом или щелчком.",
    "description_uk": "Металлические наручники, покрытые мягким плюшем. Открываются ключом или щелчком.",
    "price": 118,
    "oldprice": 131,
    "images": [
      "https://images.prom.ua/7006063113_naruchniki-sladkie-okovy.jpg",
      "https://images.prom.ua/7006063114_naruchniki-sladkie-okovy.jpg"
    ],
    "categoryId": "105010126",
    "available": true,
    "category": "bdsm",
    "params": [
      {
        "name": "Цвет",
        "value": "Черный"
      },
      {
        "name": "Материал",
        "value": "Металл"
      }
    ]
  },
  {
    "id": "1559966895",
    "name_ru": "Скотч для бондажа - Черный",
    "name_uk": "Скотч для бондажу - Чорний",
    "description_ru": "БДСМ скотч для тела. Ширина: 5 см, Длина: 10 м.",
    "description_uk": "БДСМ скотч для тела. Ширина: 5 см, Длина: 10 м.",
    "price": 136,
    "oldprice": 152,
    "images": [
      "https://images.prom.ua/7006063116_skotch-dlya-bondazha.jpg",
      "https://images.prom.ua/7006063118_skotch-dlya-bondazha.jpg"
    ],
    "categoryId": "105010126",
    "available": true,
    "category": "bdsm",
    "params": [
      {
        "name": "Цвет",
        "value": "Черный"
      },
      {
        "name": "Материал",
        "value": "Полиуретан"
      }
    ]
  },
  {
    "id": "1559966896",
    "name_ru": "Кожаный ошейник с поводком - Черный",
    "name_uk": "Шкіряний нашийник з повідцем - Чорний",
    "description_ru": "Ошейник с поводком. Ошейник 50*5 см, длина поводка 100 см. Материал: эко-кожа, металл.",
    "description_uk": "Ошейник с поводком. Ошейник 50*5 см, длина поводка 100 см. Материал: эко-кожа, металл.",
    "price": 168,
    "oldprice": 188,
    "images": [
      "https://images.prom.ua/7034814173_kozhanyj-oshejnik-s.jpg",
      "https://images.prom.ua/7034814176_kozhanyj-oshejnik-s.jpg"
    ],
    "categoryId": "105010126",
    "available": true,
    "category": "bdsm",
    "params": [
      {
        "name": "Цвет",
        "value": "Черный"
      },
      {
        "name": "Материал",
        "value": "Искусственная кожа"
      }
    ]
  },
  {
    "id": "1559966897",
    "name_ru": "Кожаные наручники с мехом - Черный",
    "name_uk": "Шкіряні наручники з хутром - Чорний",
    "description_ru": "Кожаные наручники с искусственным мехом, соединены цепочкой. Длина 27х5 см. Материал: эко-кожа.",
    "description_uk": "Кожаные наручники с искусственным мехом, соединены цепочкой. Длина 27х5 см. Материал: эко-кожа.",
    "price": 146,
    "oldprice": 162,
    "images": [
      "https://images.prom.ua/7034814180_kozhanye-naruchniki-s.jpg",
      "https://images.prom.ua/7034814181_kozhanye-naruchniki-s.jpg"
    ],
    "categoryId": "105010126",
    "available": true,
    "category": "bdsm",
    "params": [
      {
        "name": "Цвет",
        "value": "Черный"
      },
      {
        "name": "Материал",
        "value": "Искусственная кожа"
      }
    ]
  },
  {
    "id": "1559966898",
    "name_ru": "Съедобный лубрикант FRUITS FUN 80мл - Черника",
    "name_uk": "Їстівний лубрикант FRUITS FUN 80мл - Чорниця",
    "description_ru": "Съедобный лубрикант на водной основе. Объем 80 мл. Подходит для орального и вагинального секса.",
    "description_uk": "Съедобный лубрикант на водной основе. Объем 80 мл. Подходит для орального и вагинального секса.",
    "price": 213,
    "oldprice": null,
    "images": [
      "https://images.prom.ua/6460017255_sedobnyj-lubrikant-fruits.jpg",
      "https://images.prom.ua/6460017257_sedobnyj-lubrikant-fruits.jpg"
    ],
    "categoryId": "105147973",
    "available": false,
    "category": "lubricants",
    "params": [
      {
        "name": "Основа",
        "value": "Водная"
      },
      {
        "name": "Вкус",
        "value": "Черника"
      },
      {
        "name": "Объем",
        "value": "80"
      }
    ]
  },
  {
    "id": "1559966899",
    "name_ru": "Эрекционное кольцо с уретральным катетером и вибрацией",
    "name_uk": "Ерекційне кільце з уретральним катетером і вібрацією",
    "description_ru": "Катетер из силикона. Общая длина 26,5 см. Диаметр кольца 3,2 см. Работает от 2 батареек LR41.",
    "description_uk": "Катетер из силикона. Общая длина 26,5 см. Диаметр кольца 3,2 см. Работает от 2 батареек LR41.",
    "price": 268,
    "oldprice": 301,
    "images": [
      "https://images.prom.ua/3590117949_erektsionnoe-koltso-s.jpg",
      "https://images.prom.ua/7034823678_erektsionnoe-koltso-s.jpg"
    ],
    "categoryId": "105010129",
    "available": true,
    "category": "for-him",
    "params": [
      {
        "name": "Материал",
        "value": "Силикон"
      },
      {
        "name": "Цвет",
        "value": "Черный"
      }
    ]
  },
  {
    "id": "1559966900",
    "name_ru": "БДСМ набор из 10 предметов (2) - Чёрный",
    "name_uk": "БДСМ набір із 10 предметів (2) - Чорний",
    "description_ru": "Набор из 10 предметов: маска, кляп, ошейник с поводком, наручники, поножи, плетка, шлепалка, эрекционное кольцо, кубики, зажимы.",
    "description_uk": "Набор из 10 предметов: маска, кляп, ошейник с поводком, наручники, поножи, плетка, шлепалка, эрекционное кольцо, кубики, зажимы.",
    "price": 596,
    "oldprice": 671,
    "images": [
      "https://images.prom.ua/7034814183_bdsm-nabor-iz.jpg",
      "https://images.prom.ua/7034814185_bdsm-nabor-iz.jpg"
    ],
    "categoryId": "105010126",
    "available": true,
    "category": "bdsm",
    "params": [
      {
        "name": "Цвет",
        "value": "Черный"
      },
      {
        "name": "Материал",
        "value": "Нейлон"
      }
    ]
  },
  {
    "id": "1559966901",
    "name_ru": "БДСМ набор из 12 предметов - Чёрный",
    "name_uk": "БДСМ набір із 12 предметів - Чорний",
    "description_ru": "Набор из 12 предметов включая анальную пробку и вибратор. Материал: эко-кожа.",
    "description_uk": "Набор из 12 предметов включая анальную пробку и вибратор. Материал: эко-кожа.",
    "price": 879,
    "oldprice": 985,
    "images": [
      "https://images.prom.ua/7032449835_bdsm-nabor-iz.jpg",
      "https://images.prom.ua/7032449836_bdsm-nabor-iz.jpg"
    ],
    "categoryId": "105010126",
    "available": true,
    "category": "bdsm",
    "params": [
      {
        "name": "Цвет",
        "value": "Черный"
      },
      {
        "name": "Материал",
        "value": "Нейлон"
      }
    ]
  },
  {
    "id": "1559966902",
    "name_ru": "БДСМ набор из 10 предметов (3) - Чёрный",
    "name_uk": "БДСМ набір із 10 предметів (3) - Чорний",
    "description_ru": "Набор из 10 предметов с бандажной веревкой. Материал: эко-кожа.",
    "description_uk": "Набор из 10 предметов с бандажной веревкой. Материал: эко-кожа.",
    "price": 610,
    "oldprice": 686,
    "images": [
      "https://images.prom.ua/7032450972_bdsm-nabor-iz.jpg",
      "https://images.prom.ua/7032450973_bdsm-nabor-iz.jpg"
    ],
    "categoryId": "105010126",
    "available": true,
    "category": "bdsm",
    "params": [
      {
        "name": "Цвет",
        "value": "Черный"
      },
      {
        "name": "Материал",
        "value": "Нейлон"
      }
    ]
  },
  {
    "id": "1559966903",
    "name_ru": "БДСМ набор для фиксации на руки, ноги и шею - Черный",
    "name_uk": "БДСМ набір для фіксації на руки, ноги та шию - Чорний",
    "description_ru": "Мягкие фиксаторы на руки, ноги и шею. Можно стирать при 30°C.",
    "description_uk": "Мягкие фиксаторы на руки, ноги и шею. Можно стирать при 30°C.",
    "price": 517,
    "oldprice": 579,
    "images": [
      "https://images.prom.ua/7034814274_bdsm-nabor-dlya.jpg",
      "https://images.prom.ua/7034814276_bdsm-nabor-dlya.jpg"
    ],
    "categoryId": "105010126",
    "available": true,
    "category": "bdsm",
    "params": [
      {
        "name": "Цвет",
        "value": "Черный"
      },
      {
        "name": "Материал",
        "value": "Полиуретан"
      }
    ]
  },
  {
    "id": "1559966904",
    "name_ru": "БДСМ Качели Fly Sex Yoga - Красный",
    "name_uk": "БДСМ Гойдалки Fly Sex Yoga - Червоний",
    "description_ru": "Качели для секса. Выдерживают до 150 кг. Регулируемые мягкие ремни. Металлические карабины.",
    "description_uk": "Качели для секса. Выдерживают до 150 кг. Регулируемые мягкие ремни. Металлические карабины.",
    "price": 704,
    "oldprice": 792,
    "images": [
      "https://images.prom.ua/7010415924_bdsm-kacheli-fly.jpg",
      "https://images.prom.ua/7010415921_bdsm-kacheli-fly.jpg"
    ],
    "categoryId": "105010126",
    "available": true,
    "category": "bdsm",
    "params": [
      {
        "name": "Цвет",
        "value": "Красный"
      },
      {
        "name": "Материал",
        "value": "Нейлон"
      }
    ]
  },
  {
    "id": "1559966906",
    "name_ru": "Полый страпон с вибрацией 19*5 см - Телесный",
    "name_uk": "Порожнистий страпон з вібрацією 19*5 см - Тілесний",
    "description_ru": "Латексный страпон с вибрацией на эластичных ремешках. Длина 19 см, диаметр 5 см.",
    "description_uk": "Латексный страпон с вибрацией на эластичных ремешках. Длина 19 см, диаметр 5 см.",
    "price": 794,
    "oldprice": 893,
    "images": [
      "https://images.prom.ua/7034829142_polyj-strapon-s.jpg",
      "https://images.prom.ua/7034829143_polyj-strapon-s.jpg"
    ],
    "categoryId": "105010131",
    "available": true,
    "category": "for-her",
    "params": [
      {
        "name": "Цвет",
        "value": "Телесный"
      },
      {
        "name": "Материал",
        "value": "Силикон"
      }
    ]
  },
  {
    "id": "1559966907",
    "name_ru": "Анальная пробка с хвостиком - Белый - 7,5*2,8 см",
    "name_uk": "Анальна пробка з хвостиком - Білий - 7,5*2,8 см",
    "description_ru": "Анальная пробка с пушистым кроличьим хвостиком. Длина хвоста 8,8 см. Размер: 7,5*2,8 см.",
    "description_uk": "Анальная пробка с пушистым кроличьим хвостиком. Длина хвоста 8,8 см. Размер: 7,5*2,8 см.",
    "price": 165,
    "oldprice": 183,
    "images": [
      "https://images.prom.ua/7034816965_analnaya-probka-s.jpg",
      "https://images.prom.ua/6408988118_analnaya-probka-s.jpg"
    ],
    "categoryId": "105010127",
    "available": true,
    "category": "bdsm",
    "params": [
      {
        "name": "Материал",
        "value": "Металл"
      },
      {
        "name": "Цвет",
        "value": "Белый"
      }
    ]
  },
  {
    "id": "1559966908",
    "name_ru": "Силиконовая анальная пробка с кристаллом - 4.2*9.5 см - Розовый",
    "name_uk": "Силіконова анальна пробка з кристалом - 4.2*9.5 см - Рожевий",
    "description_ru": "Силиконовая анальная пробка с кристаллом. Размер: 4,2*9,5 см. Цвет: розовый.",
    "description_uk": "Силиконовая анальная пробка с кристаллом. Размер: 4,2*9,5 см. Цвет: розовый.",
    "price": 191,
    "oldprice": 213,
    "images": [
      "https://images.prom.ua/7008793939_silikonovaya-analnaya-probka.jpg",
      "https://images.prom.ua/6409451334_silikonovaya-analnaya-probka.jpg"
    ],
    "categoryId": "105010127",
    "available": true,
    "category": "bdsm",
    "params": [
      {
        "name": "Материал",
        "value": "Силикон"
      },
      {
        "name": "Цвет",
        "value": "Розовый"
      }
    ]
  },
  {
    "id": "1559966909",
    "name_ru": "Стальная анальная пробка с кристаллом - 2.7*7 см",
    "name_uk": "Сталева анальна пробка з кристалом - 2.7*7 см",
    "description_ru": "Стальная анальная пробка с кристаллом в круглом основании. Размер: 2,7*7 см.",
    "description_uk": "Стальная анальная пробка с кристаллом в круглом основании. Размер: 2,7*7 см.",
    "price": 142,
    "oldprice": 156,
    "images": [
      "https://images.prom.ua/6459971072_stalnaya-analnaya-probka.jpg",
      "https://images.prom.ua/7012387023_stalnaya-analnaya-probka.jpg"
    ],
    "categoryId": "105010127",
    "available": true,
    "category": "bdsm",
    "params": [
      {
        "name": "Материал",
        "value": "Металл"
      }
    ]
  }
]